impmagic/__init__.py
impmagic/impmagic.py
impmagic-0.2.2.dist-info/licenses/LICENSE
impmagic-0.2.2.dist-info/METADATA
impmagic-0.2.2.dist-info/WHEEL
impmagic-0.2.2.dist-info/top_level.txt
impmagic-0.2.2.dist-info/RECORD
