Metadata-Version: 2.4
Name: impmagic
Version: 0.2.2
Summary: Librairie pour l'importation optimisé de module python
Home-page: https://github.com/ZephyrOff/impmagic
Author: 
License: MIT License
Project-URL: Documentation, https://github.com/ZephyrOff/impmagic
Keywords: import module zephyroff
Platform: ALL
Classifier: Development Status :: 5 - Production/Stable
Classifier: Environment :: Console
Classifier: License :: OSI Approved :: MIT License
Classifier: Programming Language :: Python :: 3
License-File: LICENSE
Dynamic: classifier
Dynamic: description
Dynamic: description-content-type
Dynamic: home-page
Dynamic: keywords
Dynamic: license
Dynamic: license-file
Dynamic: platform
Dynamic: project-url
Dynamic: summary
